pioupiou/__init__.py
boisgera_pioupiou-0.0a12.dist-info/LICENSE.txt
boisgera_pioupiou-0.0a12.dist-info/METADATA
boisgera_pioupiou-0.0a12.dist-info/WHEEL
boisgera_pioupiou-0.0a12.dist-info/top_level.txt
boisgera_pioupiou-0.0a12.dist-info/RECORD
