Metadata-Version: 2.1
Name: boisgera-pioupiou
Version: 0.0a12
Summary: A nano probabilistic programming language for Python
Home-page: https://github.com/boisgera/pioupiou
Author: Sébastien Boisgérault
Author-email: Sebastien.Boisgerault@mines-paristech.fr
License: MIT License
Platform: UNKNOWN
Classifier: Programming Language :: Python :: 3
Classifier: Development Status :: 2 - Pre-Alpha
Classifier: Intended Audience :: Education
Classifier: Topic :: Scientific/Engineering :: Mathematics
Requires-Python: >=3.8
Requires-Dist: numpy
Requires-Dist: wrapt
